{
  "name": "metadata core build",
  "root": "../",
  "www_root": "../",
  "output": "dist/metadata.core.min.js",
  "modules": {
    "common":   [
      "src/common.js",
      "src/i18n.ru.js",
      "src/meta_meta.js",
      "src/meta_mngrs.js",
      "src/meta_tabulars.js",
      "src/meta_objs.js",
      "src/meta_rest.js",
      "src/events.js"],
    "xml_to_json": "lib_ext/xml_to_json.js",
    "log": "data/log.json"
  },
  "main": "common",
  "optimize": true,
  "pack": true,
  "node": true,
  "ie": false
}